genie/libs/ops/__init__.py
genie/libs/ops/ops.json
genie/libs/ops/acl/__init__.py
genie/libs/ops/acl/acl.py
genie/libs/ops/acl/ios/__init__.py
genie/libs/ops/acl/ios/acl.py
genie/libs/ops/acl/ios/tests/__init__.py
genie/libs/ops/acl/ios/tests/acl_output.py
genie/libs/ops/acl/ios/tests/test_acl.py
genie/libs/ops/acl/iosxe/__init__.py
genie/libs/ops/acl/iosxe/acl.py
genie/libs/ops/acl/iosxe/tests/__init__.py
genie/libs/ops/acl/iosxe/tests/acl_output.py
genie/libs/ops/acl/iosxe/tests/test_acl.py
genie/libs/ops/acl/iosxr/__init__.py
genie/libs/ops/acl/iosxr/acl.py
genie/libs/ops/acl/iosxr/tests/__init__.py
genie/libs/ops/acl/iosxr/tests/acl_output.py
genie/libs/ops/acl/iosxr/tests/test_acl.py
genie/libs/ops/acl/nxos/__init__.py
genie/libs/ops/acl/nxos/acl.py
genie/libs/ops/acl/nxos/tests/__init__.py
genie/libs/ops/acl/nxos/tests/acl_output.py
genie/libs/ops/acl/nxos/tests/test_acl.py
genie/libs/ops/acl/tests/__init__.py
genie/libs/ops/acl/tests/ios/__init__.py
genie/libs/ops/acl/tests/ios/acl_output.py
genie/libs/ops/acl/tests/ios/test_acl.py
genie/libs/ops/acl/tests/iosxe/__init__.py
genie/libs/ops/acl/tests/iosxe/acl_output.py
genie/libs/ops/acl/tests/iosxe/test_acl.py
genie/libs/ops/acl/tests/iosxr/__init__.py
genie/libs/ops/acl/tests/iosxr/acl_output.py
genie/libs/ops/acl/tests/iosxr/test_acl.py
genie/libs/ops/arp/__init__.py
genie/libs/ops/arp/arp.py
genie/libs/ops/arp/ios/__init__.py
genie/libs/ops/arp/ios/arp.py
genie/libs/ops/arp/ios/tests/__init__.py
genie/libs/ops/arp/ios/tests/arp_output.py
genie/libs/ops/arp/ios/tests/test_arp.py
genie/libs/ops/arp/iosxe/__init__.py
genie/libs/ops/arp/iosxe/arp.py
genie/libs/ops/arp/iosxe/tests/__init__.py
genie/libs/ops/arp/iosxe/tests/arp_output.py
genie/libs/ops/arp/iosxe/tests/test_arp.py
genie/libs/ops/arp/iosxr/__init__.py
genie/libs/ops/arp/iosxr/arp.py
genie/libs/ops/arp/iosxr/tests/__init__.py
genie/libs/ops/arp/iosxr/tests/arp_output.py
genie/libs/ops/arp/iosxr/tests/test_arp.py
genie/libs/ops/arp/nxos/__init__.py
genie.libs.ops-25.9.dist-info/METADATA
genie.libs.ops-25.9.dist-info/WHEEL
genie.libs.ops-25.9.dist-info/top_level.txt
genie.libs.ops-25.9.dist-info/RECORD
